Metadata-Version: 2.0
Name: shipane-sdk
Version: 1.5.1
Summary: 实盘易（ShiPanE）Python SDK，通达信自动化交易 API。
Home-page: https://github.com/sinall/ShiPanE-Python-SDK
Author: sinall
Author-email: gaoruinan@163.com
License: MIT
Requires-Dist: apscheduler
Requires-Dist: bs4
Requires-Dist: cssselect
Requires-Dist: html5lib
Requires-Dist: lxml
Requires-Dist: pandas
Requires-Dist: pyyaml
Requires-Dist: requests
Requires-Dist: rqopen-client
Requires-Dist: six
Requires-Dist: tushare
Provides-Extra: dev
Provides-Extra: test
